[
 {
   "Q": "Now on Tap can anticipate your needs in the moment. With a simple tap, get an instant shortcut to just the right answers at exactly the right time.",
   "O1": "7845",
   "O2": "asad",
   "O3": "789",
   "O4": "asxsa",
   "A": 2
 },
 {
   "Q": "Now on Tap can anticipate your needs in the moment. With a simple tap, get an instant shortcut to just the right answers at exactly the right time.",
   "O1": "qqw",
   "O2": "12",
   "O3": "swed",
   "O4": "qsd",
   "A": 1
 },
 {
   "Q": "Now on Tap can anticipate your needs in the moment. With a simple tap, get an instant shortcut to just the right answers at exactly the right time.",
   "O1": "qqw",
   "O2": "13",
   "O3": "swed",
   "O4": "qsd",
   "A": 2
 },
 {
   "Q": "Now on Tap can anticipate your needs in the moment. With a simple tap, get an instant shortcut to just the right answers at exactly the right time.",
   "O1": "qqw",
   "O2": "14",
   "O3": "swed",
   "O4": "qsd",
   "A": 3
 },
 {
   "Q": "Now on Tap can anticipate your needs in the moment. With a simple tap, get an instant shortcut to just the right answers at exactly the right time.",
   "O1": "qqw",
   "O2": "15",
   "O3": "swed",
   "O4": "qsd",
   "A": 4
 },
 {
   "Q": "Now on Tap can anticipate your needs in the moment. With a simple tap, get an instant shortcut to just the right answers at exactly the right time.",
   "O1": "qqw",
   "O2": "16",
   "O3": "swed",
   "O4": "qsd",
   "A": 5
 },
 {
   "Q": "Now on Tap can anticipate your needs in the moment. With a simple tap, get an instant shortcut to just the right answers at exactly the right time.",
   "O1": "qqw",
   "O2": "17",
   "O3": "swed",
   "O4": "qsd",
   "A": 6
 },
 {
   "Q": "Now on Tap can anticipate your needs in the moment. With a simple tap, get an instant shortcut to just the right answers at exactly the right time.",
   "O1": "qqw",
   "O2": "18",
   "O3": "swed",
   "O4": "qsd",
   "A": 7
 },
 {
   "Q": "Now on Tap can anticipate your needs in the moment. With a simple tap, get an instant shortcut to just the right answers at exactly the right time.",
   "O1": "qqw",
   "O2": "19",
   "O3": "swed",
   "O4": "qsd",
   "A": 8
 },
 {
   "Q": "Now on Tap can anticipate your needs in the moment. With a simple tap, get an instant shortcut to just the right answers at exactly the right time.",
   "O1": "qqw",
   "O2": "20",
   "O3": "swed",
   "O4": "qsd",
   "A": 9
 },
 {
   "Q": "Now on Tap can anticipate your needs in the moment. With a simple tap, get an instant shortcut to just the right answers at exactly the right time.",
   "O1": "qqw",
   "O2": "21",
   "O3": "swed",
   "O4": "qsd",
   "A": 10
 },
 {
   "Q": "Now on Tap can anticipate your needs in the moment. With a simple tap, get an instant shortcut to just the right answers at exactly the right time.",
   "O1": "qqw",
   "O2": "22",
   "O3": "swed",
   "O4": "qsd",
   "A": 11
 },
 {
   "Q": "Now on Tap can anticipate your needs in the moment. With a simple tap, get an instant shortcut to just the right answers at exactly the right time.",
   "O1": "qqw",
   "O2": "23",
   "O3": "swed",
   "O4": "qsd",
   "A": 12
 },
 {
   "Q": "Now on Tap can anticipate your needs in the moment. With a simple tap, get an instant shortcut to just the right answers at exactly the right time.",
   "O1": "qqw",
   "O2": "24",
   "O3": "swed",
   "O4": "qsd",
   "A": 13
 },
 {
   "Q": "Now on Tap can anticipate your needs in the moment. With a simple tap, get an instant shortcut to just the right answers at exactly the right time.",
   "O1": "qqw",
   "O2": "25",
   "O3": "swed",
   "O4": "qsd",
   "A": 14
 },
 {
   "Q": "Now on Tap can anticipate your needs in the moment. With a simple tap, get an instant shortcut to just the right answers at exactly the right time.",
   "O1": "qqw",
   "O2": "26",
   "O3": "swed",
   "O4": "qsd",
   "A": 15
 },
 {
   "Q": "Now on Tap can anticipate your needs in the moment. With a simple tap, get an instant shortcut to just the right answers at exactly the right time.",
   "O1": "qqw",
   "O2": "27",
   "O3": "swed",
   "O4": "qsd",
   "A": 16
 },
 {
   "Q": "Now on Tap can anticipate your needs in the moment. With a simple tap, get an instant shortcut to just the right answers at exactly the right time.",
   "O1": "qqw",
   "O2": "28",
   "O3": "swed",
   "O4": "qsd",
   "A": 17
 },
 {
   "Q": "Now on Tap can anticipate your needs in the moment. With a simple tap, get an instant shortcut to just the right answers at exactly the right time.",
   "O1": "qqw",
   "O2": "29",
   "O3": "swed",
   "O4": "qsd",
   "A": 18
 },
 {
   "Q": "Now on Tap can anticipate your needs in the moment. With a simple tap, get an instant shortcut to just the right answers at exactly the right time.",
   "O1": "qqw",
   "O2": "30",
   "O3": "swed",
   "O4": "qsd",
   "A": 19
 },
 {
   "Q": "Now on Tap can anticipate your needs in the moment. With a simple tap, get an instant shortcut to just the right answers at exactly the right time.",
   "O1": "qqw",
   "O2": "31",
   "O3": "swed",
   "O4": "qsd",
   "A": 20
 },
 {
   "Q": "Now on Tap can anticipate your needs in the moment. With a simple tap, get an instant shortcut to just the right answers at exactly the right time.",
   "O1": "qqw",
   "O2": "32",
   "O3": "swed",
   "O4": "qsd",
   "A": 21
 },
 {
   "Q": "Now on Tap can anticipate your needs in the moment. With a simple tap, get an instant shortcut to just the right answers at exactly the right time.",
   "O1": "qqw",
   "O2": "33",
   "O3": "swed",
   "O4": "qsd",
   "A": 22
 },
 {
   "Q": "Now on Tap can anticipate your needs in the moment. With a simple tap, get an instant shortcut to just the right answers at exactly the right time.",
   "O1": "qqw",
   "O2": "34",
   "O3": "swed",
   "O4": "qsd",
   "A": 23
 },
 {
   "Q": "Now on Tap can anticipate your needs in the moment. With a simple tap, get an instant shortcut to just the right answers at exactly the right time.",
   "O1": "qqw",
   "O2": "35",
   "O3": "swed",
   "O4": "qsd",
   "A": 24
 },
 {
   "Q": "Now on Tap can anticipate your needs in the moment. With a simple tap, get an instant shortcut to just the right answers at exactly the right time.",
   "O1": "qqw",
   "O2": "36",
   "O3": "swed",
   "O4": "qsd",
   "A": 25
 },
 {
   "Q": "Now on Tap can anticipate your needs in the moment. With a simple tap, get an instant shortcut to just the right answers at exactly the right time.",
   "O1": "qqw",
   "O2": "37",
   "O3": "swed",
   "O4": "qsd",
   "A": 26
 },
 {
   "Q": "Now on Tap can anticipate your needs in the moment. With a simple tap, get an instant shortcut to just the right answers at exactly the right time.",
   "O1": "qqw",
   "O2": "38",
   "O3": "swed",
   "O4": "qsd",
   "A": 27
 },
 {
   "Q": "Now on Tap can anticipate your needs in the moment. With a simple tap, get an instant shortcut to just the right answers at exactly the right time.",
   "O1": "qqw",
   "O2": "39",
   "O3": "swed",
   "O4": "qsd",
   "A": 28
 },
 {
   "Q": "Now on Tap can anticipate your needs in the moment. With a simple tap, get an instant shortcut to just the right answers at exactly the right time.",
   "O1": "qqw",
   "O2": "40",
   "O3": "swed",
   "O4": "qsd",
   "A": 29
 },
 {
   "Q": "Now on Tap can anticipate your needs in the moment. With a simple tap, get an instant shortcut to just the right answers at exactly the right time.",
   "O1": "qqw",
   "O2": "41",
   "O3": "swed",
   "O4": "qsd",
   "A": 30
 },
 {
   "Q": "Now on Tap can anticipate your needs in the moment. With a simple tap, get an instant shortcut to just the right answers at exactly the right time.",
   "O1": "qqw",
   "O2": "42",
   "O3": "swed",
   "O4": "qsd",
   "A": 31
 },
 {
   "Q": "Now on Tap can anticipate your needs in the moment. With a simple tap, get an instant shortcut to just the right answers at exactly the right time.",
   "O1": "qqw",
   "O2": "43",
   "O3": "swed",
   "O4": "qsd",
   "A": 32
 },
 {
   "Q": "Now on Tap can anticipate your needs in the moment. With a simple tap, get an instant shortcut to just the right answers at exactly the right time.",
   "O1": "qqw",
   "O2": "44",
   "O3": "swed",
   "O4": "qsd",
   "A": 33
 },
 {
   "Q": "Now on Tap can anticipate your needs in the moment. With a simple tap, get an instant shortcut to just the right answers at exactly the right time.",
   "O1": "qqw",
   "O2": "45",
   "O3": "swed",
   "O4": "qsd",
   "A": 34
 },
 {
   "Q": "Now on Tap can anticipate your needs in the moment. With a simple tap, get an instant shortcut to just the right answers at exactly the right time.",
   "O1": "qqw",
   "O2": "46",
   "O3": "swed",
   "O4": "qsd",
   "A": 35
 },
 {
   "Q": "Now on Tap can anticipate your needs in the moment. With a simple tap, get an instant shortcut to just the right answers at exactly the right time.",
   "O1": "qqw",
   "O2": "47",
   "O3": "swed",
   "O4": "qsd",
   "A": 36
 },
 {
   "Q": "Now on Tap can anticipate your needs in the moment. With a simple tap, get an instant shortcut to just the right answers at exactly the right time.",
   "O1": "qqw",
   "O2": "48",
   "O3": "swed",
   "O4": "qsd",
   "A": 37
 },
 {
   "Q": "Now on Tap can anticipate your needs in the moment. With a simple tap, get an instant shortcut to just the right answers at exactly the right time.",
   "O1": "qqw",
   "O2": "49",
   "O3": "swed",
   "O4": "qsd",
   "A": 38
 },
 {
   "Q": "Now on Tap can anticipate your needs in the moment. With a simple tap, get an instant shortcut to just the right answers at exactly the right time.",
   "O1": "qqw",
   "O2": "50",
   "O3": "swed",
   "O4": "qsd",
   "A": 39
 },
 {
   "Q": "Now on Tap can anticipate your needs in the moment. With a simple tap, get an instant shortcut to just the right answers at exactly the right time.",
   "O1": "qqw",
   "O2": "51",
   "O3": "swed",
   "O4": "qsd",
   "A": 40
 },
 {
   "Q": "Now on Tap can anticipate your needs in the moment. With a simple tap, get an instant shortcut to just the right answers at exactly the right time.",
   "O1": "qqw",
   "O2": "52",
   "O3": "swed",
   "O4": "qsd",
   "A": 41
 },
 {
   "Q": "Now on Tap can anticipate your needs in the moment. With a simple tap, get an instant shortcut to just the right answers at exactly the right time.",
   "O1": "qqw",
   "O2": "53",
   "O3": "swed",
   "O4": "qsd",
   "A": 42
 },
 {
   "Q": "Now on Tap can anticipate your needs in the moment. With a simple tap, get an instant shortcut to just the right answers at exactly the right time.",
   "O1": "qqw",
   "O2": "54",
   "O3": "swed",
   "O4": "qsd",
   "A": 43
 },
 {
   "Q": "Now on Tap can anticipate your needs in the moment. With a simple tap, get an instant shortcut to just the right answers at exactly the right time.",
   "O1": "qqw",
   "O2": "55",
   "O3": "swed",
   "O4": "qsd",
   "A": 44
 },
 {
   "Q": "Now on Tap can anticipate your needs in the moment. With a simple tap, get an instant shortcut to just the right answers at exactly the right time.",
   "O1": "qqw",
   "O2": "56",
   "O3": "swed",
   "O4": "qsd",
   "A": 45
 },
 {
   "Q": "Now on Tap can anticipate your needs in the moment. With a simple tap, get an instant shortcut to just the right answers at exactly the right time.",
   "O1": "qqw",
   "O2": "57",
   "O3": "swed",
   "O4": "qsd",
   "A": 46
 },
 {
   "Q": "Now on Tap can anticipate your needs in the moment. With a simple tap, get an instant shortcut to just the right answers at exactly the right time.",
   "O1": "qqw",
   "O2": "58",
   "O3": "swed",
   "O4": "qsd",
   "A": 47
 },
 {
   "Q": "Now on Tap can anticipate your needs in the moment. With a simple tap, get an instant shortcut to just the right answers at exactly the right time.",
   "O1": "qqw",
   "O2": "59",
   "O3": "swed",
   "O4": "qsd",
   "A": 48
 },
 {
   "Q": "Now on Tap can anticipate your needs in the moment. With a simple tap, get an instant shortcut to just the right answers at exactly the right time.",
   "O1": "qqw",
   "O2": "60",
   "O3": "swed",
   "O4": "qsd",
   "A": 49
 },
 {
   "Q": "Now on Tap can anticipate your needs in the moment. With a simple tap, get an instant shortcut to just the right answers at exactly the right time.",
   "O1": "qqw",
   "O2": "61",
   "O3": "swed",
   "O4": "qsd",
   "A": 50
 },
 {
   "Q": "Now on Tap can anticipate your needs in the moment. With a simple tap, get an instant shortcut to just the right answers at exactly the right time.",
   "O1": "qqw",
   "O2": "62",
   "O3": "swed",
   "O4": "qsd",
   "A": 51
 },
 {
   "Q": "Now on Tap can anticipate your needs in the moment. With a simple tap, get an instant shortcut to just the right answers at exactly the right time.",
   "O1": "qqw",
   "O2": "63",
   "O3": "swed",
   "O4": "qsd",
   "A": 52
 },
 {
   "Q": "Now on Tap can anticipate your needs in the moment. With a simple tap, get an instant shortcut to just the right answers at exactly the right time.",
   "O1": "qqw",
   "O2": "64",
   "O3": "swed",
   "O4": "qsd",
   "A": 53
 },
 {
   "Q": "Now on Tap can anticipate your needs in the moment. With a simple tap, get an instant shortcut to just the right answers at exactly the right time.",
   "O1": "qqw",
   "O2": "65",
   "O3": "swed",
   "O4": "qsd",
   "A": 54
 },
 {
   "Q": "Now on Tap can anticipate your needs in the moment. With a simple tap, get an instant shortcut to just the right answers at exactly the right time.",
   "O1": "qqw",
   "O2": "66",
   "O3": "swed",
   "O4": "qsd",
   "A": 55
 },
 {
   "Q": "Now on Tap can anticipate your needs in the moment. With a simple tap, get an instant shortcut to just the right answers at exactly the right time.",
   "O1": "qqw",
   "O2": "67",
   "O3": "swed",
   "O4": "qsd",
   "A": 56
 },
 {
   "Q": "Now on Tap can anticipate your needs in the moment. With a simple tap, get an instant shortcut to just the right answers at exactly the right time.",
   "O1": "qqw",
   "O2": "68",
   "O3": "swed",
   "O4": "qsd",
   "A": 57
 },
 {
   "Q": "Now on Tap can anticipate your needs in the moment. With a simple tap, get an instant shortcut to just the right answers at exactly the right time.",
   "O1": "qqw",
   "O2": "69",
   "O3": "swed",
   "O4": "qsd",
   "A": 58
 },
 {
   "Q": "Now on Tap can anticipate your needs in the moment. With a simple tap, get an instant shortcut to just the right answers at exactly the right time.",
   "O1": "qqw",
   "O2": "70",
   "O3": "swed",
   "O4": "qsd",
   "A": 59
 },
 {
   "Q": "Now on Tap can anticipate your needs in the moment. With a simple tap, get an instant shortcut to just the right answers at exactly the right time.",
   "O1": "qqw",
   "O2": "71",
   "O3": "swed",
   "O4": "qsd",
   "A": 60
 },
 {
   "Q": "Now on Tap can anticipate your needs in the moment. With a simple tap, get an instant shortcut to just the right answers at exactly the right time.",
   "O1": "qqw",
   "O2": "72",
   "O3": "swed",
   "O4": "qsd",
   "A": 61
 },
 {
   "Q": "Now on Tap can anticipate your needs in the moment. With a simple tap, get an instant shortcut to just the right answers at exactly the right time.",
   "O1": "qqw",
   "O2": "73",
   "O3": "swed",
   "O4": "qsd",
   "A": 62
 },
 {
   "Q": "Now on Tap can anticipate your needs in the moment. With a simple tap, get an instant shortcut to just the right answers at exactly the right time.",
   "O1": "qqw",
   "O2": "74",
   "O3": "swed",
   "O4": "qsd",
   "A": 63
 },
 {
   "Q": "Now on Tap can anticipate your needs in the moment. With a simple tap, get an instant shortcut to just the right answers at exactly the right time.",
   "O1": "qqw",
   "O2": "75",
   "O3": "swed",
   "O4": "qsd",
   "A": 64
 },
 {
   "Q": "Now on Tap can anticipate your needs in the moment. With a simple tap, get an instant shortcut to just the right answers at exactly the right time.",
   "O1": "qqw",
   "O2": "76",
   "O3": "swed",
   "O4": "qsd",
   "A": 65
 },
 {
   "Q": "Now on Tap can anticipate your needs in the moment. With a simple tap, get an instant shortcut to just the right answers at exactly the right time.",
   "O1": "qqw",
   "O2": "77",
   "O3": "swed",
   "O4": "qsd",
   "A": 66
 },
 {
   "Q": "Now on Tap can anticipate your needs in the moment. With a simple tap, get an instant shortcut to just the right answers at exactly the right time.",
   "O1": "qqw",
   "O2": "78",
   "O3": "swed",
   "O4": "qsd",
   "A": 67
 },
 {
   "Q": "Now on Tap can anticipate your needs in the moment. With a simple tap, get an instant shortcut to just the right answers at exactly the right time.",
   "O1": "qqw",
   "O2": "79",
   "O3": "swed",
   "O4": "qsd",
   "A": 68
 },
 {
   "Q": "Now on Tap can anticipate your needs in the moment. With a simple tap, get an instant shortcut to just the right answers at exactly the right time.",
   "O1": "qqw",
   "O2": "80",
   "O3": "swed",
   "O4": "qsd",
   "A": 69
 },
 {
   "Q": "Now on Tap can anticipate your needs in the moment. With a simple tap, get an instant shortcut to just the right answers at exactly the right time.",
   "O1": "qqw",
   "O2": "81",
   "O3": "swed",
   "O4": "qsd",
   "A": 70
 },
 {
   "Q": "Now on Tap can anticipate your needs in the moment. With a simple tap, get an instant shortcut to just the right answers at exactly the right time.",
   "O1": "qqw",
   "O2": "82",
   "O3": "swed",
   "O4": "qsd",
   "A": 71
 },
 {
   "Q": "Now on Tap can anticipate your needs in the moment. With a simple tap, get an instant shortcut to just the right answers at exactly the right time.",
   "O1": "qqw",
   "O2": "83",
   "O3": "swed",
   "O4": "qsd",
   "A": 72
 },
 {
   "Q": "Now on Tap can anticipate your needs in the moment. With a simple tap, get an instant shortcut to just the right answers at exactly the right time.",
   "O1": "qqw",
   "O2": "84",
   "O3": "swed",
   "O4": "qsd",
   "A": 73
 },
 {
   "Q": "Now on Tap can anticipate your needs in the moment. With a simple tap, get an instant shortcut to just the right answers at exactly the right time.",
   "O1": "qqw",
   "O2": "85",
   "O3": "swed",
   "O4": "qsd",
   "A": 74
 },
 {
   "Q": "Now on Tap can anticipate your needs in the moment. With a simple tap, get an instant shortcut to just the right answers at exactly the right time.",
   "O1": "qqw",
   "O2": "86",
   "O3": "swed",
   "O4": "qsd",
   "A": 75
 },
 {
   "Q": "Now on Tap can anticipate your needs in the moment. With a simple tap, get an instant shortcut to just the right answers at exactly the right time.",
   "O1": "qqw",
   "O2": "87",
   "O3": "swed",
   "O4": "qsd",
   "A": 76
 },
 {
   "Q": "Now on Tap can anticipate your needs in the moment. With a simple tap, get an instant shortcut to just the right answers at exactly the right time.",
   "O1": "qqw",
   "O2": "88",
   "O3": "swed",
   "O4": "qsd",
   "A": 77
 },
 {
   "Q": "Now on Tap can anticipate your needs in the moment. With a simple tap, get an instant shortcut to just the right answers at exactly the right time.",
   "O1": "qqw",
   "O2": "89",
   "O3": "swed",
   "O4": "qsd",
   "A": 78
 },
 {
   "Q": "Now on Tap can anticipate your needs in the moment. With a simple tap, get an instant shortcut to just the right answers at exactly the right time.",
   "O1": "qqw",
   "O2": "90",
   "O3": "swed",
   "O4": "qsd",
   "A": 79
 },
 {
   "Q": "Now on Tap can anticipate your needs in the moment. With a simple tap, get an instant shortcut to just the right answers at exactly the right time.",
   "O1": "qqw",
   "O2": "91",
   "O3": "swed",
   "O4": "qsd",
   "A": 80
 },
 {
   "Q": "Now on Tap can anticipate your needs in the moment. With a simple tap, get an instant shortcut to just the right answers at exactly the right time.",
   "O1": "qqw",
   "O2": "92",
   "O3": "swed",
   "O4": "qsd",
   "A": 81
 },
 {
   "Q": "Now on Tap can anticipate your needs in the moment. With a simple tap, get an instant shortcut to just the right answers at exactly the right time.",
   "O1": "qqw",
   "O2": "93",
   "O3": "swed",
   "O4": "qsd",
   "A": 82
 },
 {
   "Q": "Now on Tap can anticipate your needs in the moment. With a simple tap, get an instant shortcut to just the right answers at exactly the right time.",
   "O1": "qqw",
   "O2": "94",
   "O3": "swed",
   "O4": "qsd",
   "A": 83
 },
 {
   "Q": "Now on Tap can anticipate your needs in the moment. With a simple tap, get an instant shortcut to just the right answers at exactly the right time.",
   "O1": "qqw",
   "O2": "95",
   "O3": "swed",
   "O4": "qsd",
   "A": 84
 },
 {
   "Q": "Now on Tap can anticipate your needs in the moment. With a simple tap, get an instant shortcut to just the right answers at exactly the right time.",
   "O1": "qqw",
   "O2": "96",
   "O3": "swed",
   "O4": "qsd",
   "A": 85
 },
 {
   "Q": "Now on Tap can anticipate your needs in the moment. With a simple tap, get an instant shortcut to just the right answers at exactly the right time.",
   "O1": "qqw",
   "O2": "97",
   "O3": "swed",
   "O4": "qsd",
   "A": 86
 },
 {
   "Q": "Now on Tap can anticipate your needs in the moment. With a simple tap, get an instant shortcut to just the right answers at exactly the right time.",
   "O1": "qqw",
   "O2": "98",
   "O3": "swed",
   "O4": "qsd",
   "A": 87
 },
 {
   "Q": "Now on Tap can anticipate your needs in the moment. With a simple tap, get an instant shortcut to just the right answers at exactly the right time.",
   "O1": "qqw",
   "O2": "99",
   "O3": "swed",
   "O4": "qsd",
   "A": 88
 },
 {
   "Q": "Now on Tap can anticipate your needs in the moment. With a simple tap, get an instant shortcut to just the right answers at exactly the right time.",
   "O1": "qqw",
   "O2": "100",
   "O3": "swed",
   "O4": "qsd",
   "A": 89
 },
 {
   "Q": "Now on Tap can anticipate your needs in the moment. With a simple tap, get an instant shortcut to just the right answers at exactly the right time.",
   "O1": "qqw",
   "O2": "101",
   "O3": "swed",
   "O4": "qsd",
   "A": 90
 },
 {
   "Q": "Now on Tap can anticipate your needs in the moment. With a simple tap, get an instant shortcut to just the right answers at exactly the right time.",
   "O1": "qqw",
   "O2": "102",
   "O3": "swed",
   "O4": "qsd",
   "A": 91
 },
 {
   "Q": "Now on Tap can anticipate your needs in the moment. With a simple tap, get an instant shortcut to just the right answers at exactly the right time.",
   "O1": "qqw",
   "O2": "103",
   "O3": "swed",
   "O4": "qsd",
   "A": 92
 },
 {
   "Q": "Now on Tap can anticipate your needs in the moment. With a simple tap, get an instant shortcut to just the right answers at exactly the right time.",
   "O1": "qqw",
   "O2": "104",
   "O3": "swed",
   "O4": "qsd",
   "A": 93
 },
 {
   "Q": "Now on Tap can anticipate your needs in the moment. With a simple tap, get an instant shortcut to just the right answers at exactly the right time.",
   "O1": "qqw",
   "O2": "105",
   "O3": "swed",
   "O4": "qsd",
   "A": 94
 },
 {
   "Q": "Now on Tap can anticipate your needs in the moment. With a simple tap, get an instant shortcut to just the right answers at exactly the right time.",
   "O1": "qqw",
   "O2": "106",
   "O3": "swed",
   "O4": "qsd",
   "A": 95
 },
 {
   "Q": "Now on Tap can anticipate your needs in the moment. With a simple tap, get an instant shortcut to just the right answers at exactly the right time.",
   "O1": "qqw",
   "O2": "107",
   "O3": "swed",
   "O4": "qsd",
   "A": 96
 },
 {
   "Q": "Now on Tap can anticipate your needs in the moment. With a simple tap, get an instant shortcut to just the right answers at exactly the right time.",
   "O1": "qqw",
   "O2": "108",
   "O3": "swed",
   "O4": "qsd",
   "A": 97
 },
 {
   "Q": "Now on Tap can anticipate your needs in the moment. With a simple tap, get an instant shortcut to just the right answers at exactly the right time.",
   "O1": "qqw",
   "O2": "109",
   "O3": "swed",
   "O4": "qsd",
   "A": 98
 },
 {
   "Q": "Now on Tap can anticipate your needs in the moment. With a simple tap, get an instant shortcut to just the right answers at exactly the right time.",
   "O1": "qqw",
   "O2": "110",
   "O3": "swed",
   "O4": "qsd",
   "A": 99
 },
 {
   "Q": "Now on Tap can anticipate your needs in the moment. With a simple tap, get an instant shortcut to just the right answers at exactly the right time.",
   "O1": "qqw",
   "O2": "111",
   "O3": "swed",
   "O4": "qsd",
   "A": 100
 },
 {
   "Q": "Now on Tap can anticipate your needs in the moment. With a simple tap, get an instant shortcut to just the right answers at exactly the right time.",
   "O1": "qqw",
   "O2": "112",
   "O3": "swed",
   "O4": "qsd",
   "A": 101
 },
 {
   "Q": "Now on Tap can anticipate your needs in the moment. With a simple tap, get an instant shortcut to just the right answers at exactly the right time.",
   "O1": "qqw",
   "O2": "113",
   "O3": "swed",
   "O4": "qsd",
   "A": 102
 },
 {
   "Q": "Now on Tap can anticipate your needs in the moment. With a simple tap, get an instant shortcut to just the right answers at exactly the right time.",
   "O1": "qqw",
   "O2": "114",
   "O3": "swed",
   "O4": "qsd",
   "A": 103
 },
 {
   "Q": "Now on Tap can anticipate your needs in the moment. With a simple tap, get an instant shortcut to just the right answers at exactly the right time.",
   "O1": "qqw",
   "O2": "115",
   "O3": "swed",
   "O4": "qsd",
   "A": 104
 },
 {
   "Q": "Now on Tap can anticipate your needs in the moment. With a simple tap, get an instant shortcut to just the right answers at exactly the right time.",
   "O1": "qqw",
   "O2": "116",
   "O3": "swed",
   "O4": "qsd",
   "A": 105
 },
 {
   "Q": "Now on Tap can anticipate your needs in the moment. With a simple tap, get an instant shortcut to just the right answers at exactly the right time.",
   "O1": "qqw",
   "O2": "117",
   "O3": "swed",
   "O4": "qsd",
   "A": 106
 },
 {
   "Q": "Now on Tap can anticipate your needs in the moment. With a simple tap, get an instant shortcut to just the right answers at exactly the right time.",
   "O1": "qqw",
   "O2": "118",
   "O3": "swed",
   "O4": "qsd",
   "A": 107
 },
 {
   "Q": "Now on Tap can anticipate your needs in the moment. With a simple tap, get an instant shortcut to just the right answers at exactly the right time.",
   "O1": "qqw",
   "O2": "119",
   "O3": "swed",
   "O4": "qsd",
   "A": 108
 },
 {
   "Q": "Now on Tap can anticipate your needs in the moment. With a simple tap, get an instant shortcut to just the right answers at exactly the right time.",
   "O1": "qqw",
   "O2": "120",
   "O3": "swed",
   "O4": "qsd",
   "A": 109
 },
 {
   "Q": "Now on Tap can anticipate your needs in the moment. With a simple tap, get an instant shortcut to just the right answers at exactly the right time.",
   "O1": "qqw",
   "O2": "121",
   "O3": "swed",
   "O4": "qsd",
   "A": 110
 },
 {
   "Q": "Now on Tap can anticipate your needs in the moment. With a simple tap, get an instant shortcut to just the right answers at exactly the right time.",
   "O1": "qqw",
   "O2": "122",
   "O3": "swed",
   "O4": "qsd",
   "A": 111
 },
 {
   "Q": "Now on Tap can anticipate your needs in the moment. With a simple tap, get an instant shortcut to just the right answers at exactly the right time.",
   "O1": "qqw",
   "O2": "123",
   "O3": "swed",
   "O4": "qsd",
   "A": 112
 },
 {
   "Q": "Now on Tap can anticipate your needs in the moment. With a simple tap, get an instant shortcut to just the right answers at exactly the right time.",
   "O1": "qqw",
   "O2": "124",
   "O3": "swed",
   "O4": "qsd",
   "A": 113
 },
 {
   "Q": "Now on Tap can anticipate your needs in the moment. With a simple tap, get an instant shortcut to just the right answers at exactly the right time.",
   "O1": "qqw",
   "O2": "125",
   "O3": "swed",
   "O4": "qsd",
   "A": 114
 },
 {
   "Q": "Now on Tap can anticipate your needs in the moment. With a simple tap, get an instant shortcut to just the right answers at exactly the right time.",
   "O1": "qqw",
   "O2": "126",
   "O3": "swed",
   "O4": "qsd",
   "A": 115
 },
 {
   "Q": "Now on Tap can anticipate your needs in the moment. With a simple tap, get an instant shortcut to just the right answers at exactly the right time.",
   "O1": "qqw",
   "O2": "127",
   "O3": "swed",
   "O4": "qsd",
   "A": 116
 },
 {
   "Q": "Now on Tap can anticipate your needs in the moment. With a simple tap, get an instant shortcut to just the right answers at exactly the right time.",
   "O1": "qqw",
   "O2": "128",
   "O3": "swed",
   "O4": "qsd",
   "A": 117
 },
 {
   "Q": "Now on Tap can anticipate your needs in the moment. With a simple tap, get an instant shortcut to just the right answers at exactly the right time.",
   "O1": "qqw",
   "O2": "129",
   "O3": "swed",
   "O4": "qsd",
   "A": 118
 },
 {
   "Q": "Now on Tap can anticipate your needs in the moment. With a simple tap, get an instant shortcut to just the right answers at exactly the right time.",
   "O1": "qqw",
   "O2": "130",
   "O3": "swed",
   "O4": "qsd",
   "A": 119
 },
 {
   "Q": "Now on Tap can anticipate your needs in the moment. With a simple tap, get an instant shortcut to just the right answers at exactly the right time.",
   "O1": "qqw",
   "O2": "131",
   "O3": "swed",
   "O4": "qsd",
   "A": 120
 },
 {
   "Q": "Now on Tap can anticipate your needs in the moment. With a simple tap, get an instant shortcut to just the right answers at exactly the right time.",
   "O1": "qqw",
   "O2": "132",
   "O3": "swed",
   "O4": "qsd",
   "A": 121
 },
 {
   "Q": "Now on Tap can anticipate your needs in the moment. With a simple tap, get an instant shortcut to just the right answers at exactly the right time.",
   "O1": "qqw",
   "O2": "133",
   "O3": "swed",
   "O4": "qsd",
   "A": 122
 },
 {
   "Q": "Now on Tap can anticipate your needs in the moment. With a simple tap, get an instant shortcut to just the right answers at exactly the right time.",
   "O1": "qqw",
   "O2": "134",
   "O3": "swed",
   "O4": "qsd",
   "A": 123
 },
 {
   "Q": "Now on Tap can anticipate your needs in the moment. With a simple tap, get an instant shortcut to just the right answers at exactly the right time.",
   "O1": "qqw",
   "O2": "135",
   "O3": "swed",
   "O4": "qsd",
   "A": 124
 },
 {
   "Q": "Now on Tap can anticipate your needs in the moment. With a simple tap, get an instant shortcut to just the right answers at exactly the right time.",
   "O1": "qqw",
   "O2": "136",
   "O3": "swed",
   "O4": "qsd",
   "A": 125
 },
 {
   "Q": "Now on Tap can anticipate your needs in the moment. With a simple tap, get an instant shortcut to just the right answers at exactly the right time.",
   "O1": "qqw",
   "O2": "137",
   "O3": "swed",
   "O4": "qsd",
   "A": 126
 },
 {
   "Q": "Now on Tap can anticipate your needs in the moment. With a simple tap, get an instant shortcut to just the right answers at exactly the right time.",
   "O1": "qqw",
   "O2": "138",
   "O3": "swed",
   "O4": "qsd",
   "A": 127
 },
 {
   "Q": "Now on Tap can anticipate your needs in the moment. With a simple tap, get an instant shortcut to just the right answers at exactly the right time.",
   "O1": "qqw",
   "O2": "139",
   "O3": "swed",
   "O4": "qsd",
   "A": 128
 },
 {
   "Q": "Now on Tap can anticipate your needs in the moment. With a simple tap, get an instant shortcut to just the right answers at exactly the right time.",
   "O1": "qqw",
   "O2": "140",
   "O3": "swed",
   "O4": "qsd",
   "A": 129
 },
 {
   "Q": "Now on Tap can anticipate your needs in the moment. With a simple tap, get an instant shortcut to just the right answers at exactly the right time.",
   "O1": "qqw",
   "O2": "141",
   "O3": "swed",
   "O4": "qsd",
   "A": 130
 },
 {
   "Q": "Now on Tap can anticipate your needs in the moment. With a simple tap, get an instant shortcut to just the right answers at exactly the right time.",
   "O1": "qqw",
   "O2": "142",
   "O3": "swed",
   "O4": "qsd",
   "A": 131
 },
 {
   "Q": "Now on Tap can anticipate your needs in the moment. With a simple tap, get an instant shortcut to just the right answers at exactly the right time.",
   "O1": "qqw",
   "O2": "143",
   "O3": "swed",
   "O4": "qsd",
   "A": 132
 },
 {
   "Q": "Now on Tap can anticipate your needs in the moment. With a simple tap, get an instant shortcut to just the right answers at exactly the right time.",
   "O1": "qqw",
   "O2": "144",
   "O3": "swed",
   "O4": "qsd",
   "A": 133
 },
 {
   "Q": "Now on Tap can anticipate your needs in the moment. With a simple tap, get an instant shortcut to just the right answers at exactly the right time.",
   "O1": "qqw",
   "O2": "145",
   "O3": "swed",
   "O4": "qsd",
   "A": 134
 },
 {
   "Q": "Now on Tap can anticipate your needs in the moment. With a simple tap, get an instant shortcut to just the right answers at exactly the right time.",
   "O1": "qqw",
   "O2": "146",
   "O3": "swed",
   "O4": "qsd",
   "A": 135
 },
 {
   "Q": "Now on Tap can anticipate your needs in the moment. With a simple tap, get an instant shortcut to just the right answers at exactly the right time.",
   "O1": "qqw",
   "O2": "147",
   "O3": "swed",
   "O4": "qsd",
   "A": 136
 },
 {
   "Q": "Now on Tap can anticipate your needs in the moment. With a simple tap, get an instant shortcut to just the right answers at exactly the right time.",
   "O1": "qqw",
   "O2": "148",
   "O3": "swed",
   "O4": "qsd",
   "A": 137
 },
 {
   "Q": "Now on Tap can anticipate your needs in the moment. With a simple tap, get an instant shortcut to just the right answers at exactly the right time.",
   "O1": "qqw",
   "O2": "149",
   "O3": "swed",
   "O4": "qsd",
   "A": 138
 },
 {
   "Q": "Now on Tap can anticipate your needs in the moment. With a simple tap, get an instant shortcut to just the right answers at exactly the right time.",
   "O1": "qqw",
   "O2": "150",
   "O3": "swed",
   "O4": "qsd",
   "A": 139
 },
 {
   "Q": "Now on Tap can anticipate your needs in the moment. With a simple tap, get an instant shortcut to just the right answers at exactly the right time.",
   "O1": "qqw",
   "O2": "151",
   "O3": "swed",
   "O4": "qsd",
   "A": 140
 },
 {
   "Q": "Now on Tap can anticipate your needs in the moment. With a simple tap, get an instant shortcut to just the right answers at exactly the right time.",
   "O1": "qqw",
   "O2": "152",
   "O3": "swed",
   "O4": "qsd",
   "A": 141
 },
 {
   "Q": "Now on Tap can anticipate your needs in the moment. With a simple tap, get an instant shortcut to just the right answers at exactly the right time.",
   "O1": "qqw",
   "O2": "153",
   "O3": "swed",
   "O4": "qsd",
   "A": 142
 },
 {
   "Q": "Now on Tap can anticipate your needs in the moment. With a simple tap, get an instant shortcut to just the right answers at exactly the right time.",
   "O1": "qqw",
   "O2": "154",
   "O3": "swed",
   "O4": "qsd",
   "A": 143
 },
 {
   "Q": "Now on Tap can anticipate your needs in the moment. With a simple tap, get an instant shortcut to just the right answers at exactly the right time.",
   "O1": "qqw",
   "O2": "155",
   "O3": "swed",
   "O4": "qsd",
   "A": 144
 },
 {
   "Q": "Now on Tap can anticipate your needs in the moment. With a simple tap, get an instant shortcut to just the right answers at exactly the right time.",
   "O1": "qqw",
   "O2": "156",
   "O3": "swed",
   "O4": "qsd",
   "A": 145
 },
 {
   "Q": "Now on Tap can anticipate your needs in the moment. With a simple tap, get an instant shortcut to just the right answers at exactly the right time.",
   "O1": "qqw",
   "O2": "157",
   "O3": "swed",
   "O4": "qsd",
   "A": 146
 },
 {
   "Q": "Now on Tap can anticipate your needs in the moment. With a simple tap, get an instant shortcut to just the right answers at exactly the right time.",
   "O1": "qqw",
   "O2": "158",
   "O3": "swed",
   "O4": "qsd",
   "A": 147
 },
 {
   "Q": "Now on Tap can anticipate your needs in the moment. With a simple tap, get an instant shortcut to just the right answers at exactly the right time.",
   "O1": "qqw",
   "O2": "159",
   "O3": "swed",
   "O4": "qsd",
   "A": 148
 }
]